jmq_olt_zyxel/OLT1408A.py
jmq_olt_zyxel/__init__.py
jmq_olt_zyxel-1.0.0.dist-info/licenses/LICENSE
jmq_olt_zyxel-1.0.0.dist-info/METADATA
jmq_olt_zyxel-1.0.0.dist-info/WHEEL
jmq_olt_zyxel-1.0.0.dist-info/top_level.txt
jmq_olt_zyxel-1.0.0.dist-info/RECORD
