Metadata-Version: 2.4
Name: jmq_olt_zyxel
Version: 1.0.0
Summary: Paquete de Integración OLT Zyxel con Python
Author-email: Juanma Quijada <quijada.jm@gmail.com>
License: MIT
Project-URL: Homepage, https://github.com/juaquicar/jmq_olt_zyxel
Classifier: Programming Language :: Python :: 3
Classifier: License :: OSI Approved :: MIT License
Classifier: Operating System :: OS Independent
Requires-Python: >=3.6
License-File: LICENSE
Dynamic: license-file
